odoo10_addon_barcodes_generator_location-10.0.1.0.0-py2.7-nspkg.pth
odoo10_addon_barcodes_generator_location-10.0.1.0.0.dist-info/top_level.txt
odoo10_addon_barcodes_generator_location-10.0.1.0.0.dist-info/WHEEL
odoo10_addon_barcodes_generator_location-10.0.1.0.0.dist-info/RECORD
odoo10_addon_barcodes_generator_location-10.0.1.0.0.dist-info/metadata.json
odoo10_addon_barcodes_generator_location-10.0.1.0.0.dist-info/DESCRIPTION.rst
odoo10_addon_barcodes_generator_location-10.0.1.0.0.dist-info/METADATA
odoo10_addon_barcodes_generator_location-10.0.1.0.0.dist-info/namespace_packages.txt
odoo/addons/barcodes_generator_location/__manifest__.py
odoo/addons/barcodes_generator_location/__init__.py
odoo/addons/barcodes_generator_location/README.rst
odoo/addons/barcodes_generator_location/models/stock_location.py
odoo/addons/barcodes_generator_location/models/barcode_rule.py
odoo/addons/barcodes_generator_location/models/__init__.py
odoo/addons/barcodes_generator_location/views/stock_location.xml
odoo/addons/barcodes_generator_location/tests/__init__.py
odoo/addons/barcodes_generator_location/tests/test_barcode_generator.py
odoo/addons/barcodes_generator_location/demo/function.xml
odoo/addons/barcodes_generator_location/demo/stock_location.xml
odoo/addons/barcodes_generator_location/demo/barcode_rule.xml
odoo/addons/barcodes_generator_location/demo/ir_sequence.xml
odoo/addons/barcodes_generator_location/static/description/stock_location_sequence_generation.png
odoo/addons/barcodes_generator_location/static/description/icon.png
